tests/__init__.py
tests/test_async_youtube_notifier.py
tests/test_errors.py
tests/test_youtube_notifier.py
tests/history/__init__.py
tests/history/test_file.py
tests/history/test_inmemory.py
ytnoti/__init__.py
ytnoti/enums.py
ytnoti/errors.py
ytnoti/types.py
ytnoti/models/__init__.py
ytnoti/models/history.py
ytnoti/models/video.py
ytnoti-2.1.3.dist-info/LICENSE.md
ytnoti-2.1.3.dist-info/METADATA
ytnoti-2.1.3.dist-info/WHEEL
ytnoti-2.1.3.dist-info/top_level.txt
ytnoti-2.1.3.dist-info/RECORD
