Metadata-Version: 2.1
Name: ytnoti
Version: 2.1.3
Summary: Easy-to-use Python library for receiving YouTube push notification for video upload and edit in real-time
Home-page: https://github.com/SeoulSKY/ytnoti
Author: SeoulSKY
Author-email: contact@seoulsky.org
License: MIT
Classifier: Programming Language :: Python :: 3
Classifier: License :: OSI Approved :: MIT License
Classifier: Operating System :: OS Independent
Requires-Python: >=3.11
License-File: LICENSE.md
